slippy/__init__.py
slippy/contact/__init__.py
slippy/contact/_lubrication_utils.py
slippy/contact/_model_utils.py
slippy/contact/_step_utils.py
slippy/contact/adhesion_models.py
slippy/contact/hertz.py
slippy/contact/lubricant.py
slippy/contact/lubricant_models.py
slippy/contact/lubrication_steps.py
slippy/contact/models.py
slippy/contact/quasi_static_step.py
slippy/contact/static_step.py
slippy/contact/steps.py
slippy/contact/unified_reynolds_solver.py
slippy/contact/sub_models/_TransientSubModelABC.py
slippy/contact/sub_models/__init__.py
slippy/contact/sub_models/contact_stiffness.py
slippy/contact/sub_models/contact_time.py
slippy/contact/sub_models/dummy_value.py
slippy/contact/sub_models/epp_wear.py
slippy/contact/sub_models/fill_displacements.py
slippy/contact/sub_models/friction_coulomb_model.py
slippy/contact/sub_models/rigid_body_displacement.py
slippy/contact/sub_models/shift_surface.py
slippy/contact/sub_models/sub_surface_stress.py
slippy/contact/sub_models/tangential_partial_slip.py
slippy/contact/sub_models/tangential_pure_sliding.py
slippy/core/__init__.py
slippy/core/_elastic_sub_surface_stresses.py
slippy/core/_material_utils.py
slippy/core/_stress_utils.py
slippy/core/abcs.py
slippy/core/elastic_material.py
slippy/core/gmres.py
slippy/core/influence_matrix_utils.py
slippy/core/materials.py
slippy/core/outputs.py
slippy/core/surface_tensed_material.py
slippy/data/__init__.py
slippy/surface/ACF_class.py
slippy/surface/FFTBased.py
slippy/surface/Geometric.py
slippy/surface/Random.py
slippy/surface/Surface_class.py
slippy/surface/__init__.py
slippy/surface/_johnson_utils.py
slippy/surface/_johnsonsl.py
slippy/surface/alicona.py
slippy/surface/johnsondists.py
slippy/surface/read_tst_file.py
slippy/surface/roughness_funcs.py
slippy-0.5.2.dist-info/AUTHORS.rst
slippy-0.5.2.dist-info/LICENSE
slippy-0.5.2.dist-info/METADATA
slippy-0.5.2.dist-info/WHEEL
slippy-0.5.2.dist-info/top_level.txt
slippy-0.5.2.dist-info/RECORD
