Metadata-Version: 2.1
Name: slippy
Version: 0.5.2
Summary: A python package for tribologists
Home-page: https://github.com/mikeWShef/slippy
Author: Michael Watson
Author-email: mike.watson@sheffield.ac.uk
License: MIT license
Keywords: tribology
Platform: UNKNOWN
Classifier: Development Status :: 2 - Pre-Alpha
Classifier: Intended Audience :: Science/Research
Classifier: Natural Language :: English
Classifier: Programming Language :: Python :: 3
Classifier: Programming Language :: Python :: 3.8
Classifier: Topic :: Scientific/Engineering :: Physics
Classifier: License :: OSI Approved :: MIT License
Classifier: Operating System :: OS Independent
Requires-Python: >=3.7
License-File: LICENSE
License-File: AUTHORS.rst
Requires-Dist: sympy
Requires-Dist: scikit-image
Requires-Dist: matplotlib
Requires-Dist: numpy (<1.21,>=1.17)
Requires-Dist: scipy
Requires-Dist: numba (>=0.48.0)
Requires-Dist: wheel (>=0.33.6)
Requires-Dist: flake8 (>=3.7.8)
Requires-Dist: pyfftw
Requires-Dist: tinydb
